CHANGES.txt
LICENSE.txt
MANIFEST.in
README.txt
requirements.txt
setup.py
cron_monitor/__init__.py
cron_monitor/forms.py
cron_monitor/models.py
cron_monitor/monitor.py
cron_monitor/testscript.py
cron_monitor/timestamper.py
cron_monitor/urls.py
cron_monitor/views.py
cron_monitor/templates/cron_monitor/emailsettings_add_form.html
cron_monitor/templates/cron_monitor/emailsettings_update_form.html
cron_monitor/templates/cron_monitor/globalemailaddress_form.html
cron_monitor/templates/cron_monitor/globalemailaddress_list.html
cron_monitor/templates/cron_monitor/index.html
cron_monitor/templates/cron_monitor/settings.html
cron_monitor/templates/cron_monitor/styled_log.html
cron_monitor/templates/registration/login.html
cron_monitor/tests/__init__.py
cron_monitor/tests/test_monitor.py
cron_monitor/tests/tests.py
django_cron_monitor.egg-info/PKG-INFO
django_cron_monitor.egg-info/SOURCES.txt
django_cron_monitor.egg-info/dependency_links.txt
django_cron_monitor.egg-info/entry_points.txt
django_cron_monitor.egg-info/not-zip-safe
django_cron_monitor.egg-info/requires.txt
django_cron_monitor.egg-info/top_level.txt
docs/html/.buildinfo
docs/html/config.html
docs/html/genindex.html
docs/html/index.html
docs/html/intro.html
docs/html/objects.inv
docs/html/search.html
docs/html/searchindex.js
docs/html/usage.html
docs/html/_sources/config.txt
docs/html/_sources/index.txt
docs/html/_sources/intro.txt
docs/html/_sources/usage.txt
docs/html/_static/ajax-loader.gif
docs/html/_static/basic.css
docs/html/_static/comment-bright.png
docs/html/_static/comment-close.png
docs/html/_static/comment.png
docs/html/_static/default.css
docs/html/_static/doctools.js
docs/html/_static/down-pressed.png
docs/html/_static/down.png
docs/html/_static/file.png
docs/html/_static/jquery.js
docs/html/_static/minus.png
docs/html/_static/plus.png
docs/html/_static/pygments.css
docs/html/_static/searchtools.js
docs/html/_static/sidebar.js
docs/html/_static/underscore.js
docs/html/_static/up-pressed.png
docs/html/_static/up.png
docs/html/_static/websupport.js