Metadata-Version: 1.1
Name: django-cron-monitor
Version: 1.0.0
Summary: Cron monitor script and dashboard
Home-page: http://pypi.python.org/pypi/django-cron-monitor/
Author: Alex Irpan
Author-email: alexirpan@berkeley.edu
License: LICENSE.TXT
Platform: UNKNOWN
Classifier: Environment :: Web Environment
Classifier: Framework :: Django
Classifier: Intended Audience :: Developers
Classifier: License :: OSI Approved :: BSD License
Classifier: Operating System :: Unix
Classifier: Programming Language :: Python
Classifier: Programming Language :: Python :: 2.6
Classifier: Programming Language :: Python :: 2.7
Classifier: Topic :: Internet :: WWW/HTTP
Classifier: Topic :: Internet :: WWW/HTTP :: Dynamic Content
